{
  "148736774": {
    "id": 148736774,
    "is_bot": false,
    "first_name": "Yaroslav",
    "last_name": "Usenko",
    "username": "yarusenko",
    "language_code": "ru"
  },
  "379847453": {
    "id": 379847453,
    "is_bot": false,
    "first_name": "tre_u_mer",
    "username": "lequeer"
  },
  "385379757": {
    "id": 385379757,
    "is_bot": false,
    "first_name": "Illiah",
    "username": "amethyst_dude",
    "language_code": "ru"
  },
  "421779989": {
    "id": 421779989,
    "is_bot": false,
    "first_name": "Bogdan",
    "username": "ws_li",
    "language_code": "ru"
  },
  "432000712": {
    "id": 432000712,
    "is_bot": false,
    "first_name": "ШУ",
    "last_name": "...",
    "username": "gey007"
  },
  "475978147": {
    "id": 475978147,
    "is_bot": false,
    "first_name": "egor",
    "last_name": "sjd",
    "username": "Egor_sjd"
  },
  "505758036": {
    "id": 505758036,
    "is_bot": false,
    "first_name": "0DUN0KUU B0JIK",
    "username": "ODUN0KUU_B0JIK",
    "language_code": "ru"
  },
  "611963420": {
    "id": 611963420,
    "is_bot": false,
    "first_name": "toposhaaa",
    "last_name": "aa",
    "username": "helianthus_ss",
    "language_code": "ru"
  },
  "632485270": {
    "id": 632485270,
    "is_bot": false,
    "first_name": "Алина",
    "last_name": "Шалаева",
    "username": "LISHAShalaeva",
    "language_code": "ru"
  },
  "645647251": {
    "id": 645647251,
    "is_bot": false,
    "first_name": "anita",
    "username": "anita_posledova",
    "language_code": "ru"
  },
  "704096505": {
    "id": 704096505,
    "is_bot": false,
    "first_name": "Karpenko Daria",
    "language_code": "ru"
  },
  "1115111023": {
    "id": 1115111023,
    "is_bot": false,
    "first_name": "Стройматериалы",
    "last_name": "на Силикатном",
    "language_code": "en"
  }
}